fractal_forest/__init__.py
fractal_forest/fractal.py
fractal_forest-0.2.0.dist-info/METADATA
fractal_forest-0.2.0.dist-info/WHEEL
fractal_forest-0.2.0.dist-info/top_level.txt
fractal_forest-0.2.0.dist-info/RECORD
