Metadata-Version: 2.4
Name: fractal-forest
Version: 0.2.0
Summary: A library for managing hierarchical numerical data structures
Home-page: https://github.com/drestanto/fractal-forest
Author: Drestanto Muhammad Dyasputro
Author-email: dyas@live.com
License: MIT
Classifier: Programming Language :: Python :: 3
Classifier: License :: OSI Approved :: MIT License
Classifier: Operating System :: OS Independent
Requires-Python: >=3.7
Provides-Extra: dev
Requires-Dist: pytest; extra == "dev"
Requires-Dist: twine; extra == "dev"
